[
  {
    "workload": "YCSB low",
    "ratio": 1,
    "verdict": "Auxiliary only",
    "alignment": "Smooth scaling and zero aborts, but 0.98-1.00x means no ATCC throughput gain.",
    "points": [
      {
        "clients": 8,
        "agentTps": 70.13333333,
        "totalTps": 70.13333333,
        "backgroundTps": 0,
        "speedup": 1,
        "abortRate": 0,
        "p99Ms": 150.4647875,
        "p99Reduction": 0.005005943743,
        "tokens": 27030,
        "agentTpsCv": 0.01187261977,
        "nSeeds": 3,
        "resultClass": "matrix_mean",
        "bestBaseline": "OCC",
        "bestBaselineAgentTps": 70.13333333
      },
      {
        "clients": 16,
        "agentTps": 136.6666667,
        "totalTps": 136.6666667,
        "backgroundTps": 0,
        "speedup": 0.9970817121,
        "abortRate": 0,
        "p99Ms": 151.435581,
        "p99Reduction": -0.008445864699,
        "tokens": 27030,
        "agentTpsCv": 0.01108079677,
        "nSeeds": 3,
        "resultClass": "matrix_mean",
        "bestBaseline": "OCC",
        "bestBaselineAgentTps": 137.0666667
      },
      {
        "clients": 24,
        "agentTps": 200.1333333,
        "totalTps": 200.1333333,
        "backgroundTps": 0,
        "speedup": 0.9894528672,
        "abortRate": 0,
        "p99Ms": 153.605126,
        "p99Reduction": -0.01095321315,
        "tokens": 27030,
        "agentTpsCv": 0.002307862502,
        "nSeeds": 3,
        "resultClass": "matrix_mean",
        "bestBaseline": "Silo",
        "bestBaselineAgentTps": 202.2666667
      },
      {
        "clients": 32,
        "agentTps": 253.3333333,
        "totalTps": 253.3333333,
        "backgroundTps": 0,
        "speedup": 0.9819121446,
        "abortRate": 0,
        "p99Ms": 165.9408166,
        "p99Reduction": -0.03731726626,
        "tokens": 27030,
        "agentTpsCv": 0.01423973606,
        "nSeeds": 3,
        "resultClass": "matrix_mean",
        "bestBaseline": "Silo",
        "bestBaselineAgentTps": 258
      },
      {
        "clients": 40,
        "agentTps": 282.6666667,
        "totalTps": 282.6666667,
        "backgroundTps": 0,
        "speedup": 0.9792147806,
        "abortRate": 0,
        "p99Ms": 190.4364324,
        "p99Reduction": -0.01124882783,
        "tokens": 27030,
        "agentTpsCv": 0.07146343171,
        "nSeeds": 3,
        "resultClass": "matrix_mean",
        "bestBaseline": "OCC",
        "bestBaselineAgentTps": 288.6666667
      }
    ]
  },
  {
    "workload": "YCSB low",
    "ratio": 0.8,
    "verdict": "Usable with caveat",
    "alignment": "Agent TPS improves, but total/background TPS falls as clients increase; do not claim system-wide scaling.",
    "points": [
      {
        "clients": 8,
        "agentTps": 52.4,
        "totalTps": 3361.6,
        "backgroundTps": 3309.2,
        "speedup": 1.731277533,
        "abortRate": 0,
        "p99Ms": 152.6638285,
        "p99Reduction": 0.5298523973,
        "tokens": 27030,
        "agentTpsCv": 0.01526717557,
        "nSeeds": 3,
        "resultClass": "matrix_mean",
        "bestBaseline": "2PL-wait-die",
        "bestBaselineAgentTps": 30.26666667
      },
      {
        "clients": 16,
        "agentTps": 103.3333333,
        "totalTps": 1564.8,
        "backgroundTps": 1461.466667,
        "speedup": 1.186830015,
        "abortRate": 0,
        "p99Ms": 161.7340399,
        "p99Reduction": 0.1689752843,
        "tokens": 27030,
        "agentTpsCv": 0.005913000897,
        "nSeeds": 3,
        "resultClass": "matrix_mean",
        "bestBaseline": "OCC",
        "bestBaselineAgentTps": 87.06666667
      },
      {
        "clients": 24,
        "agentTps": 134.1333333,
        "totalTps": 1182.666667,
        "backgroundTps": 1048.533333,
        "speedup": 1.346720214,
        "abortRate": 0,
        "p99Ms": 181.3193621,
        "p99Reduction": 0.3454864742,
        "tokens": 27030,
        "agentTpsCv": 0.006207751489,
        "nSeeds": 3,
        "resultClass": "matrix_mean",
        "bestBaseline": "Polaris",
        "bestBaselineAgentTps": 99.6
      },
      {
        "clients": 32,
        "agentTps": 162.6666667,
        "totalTps": 931.4666667,
        "backgroundTps": 768.8,
        "speedup": 1.345093716,
        "abortRate": 0.0007898894155,
        "p99Ms": 209.3009564,
        "p99Reduction": 0.3269957731,
        "tokens": 27051.40143,
        "agentTpsCv": 0.02719780332,
        "nSeeds": 3,
        "resultClass": "matrix_mean",
        "bestBaseline": "Silo",
        "bestBaselineAgentTps": 120.9333333
      },
      {
        "clients": 40,
        "agentTps": 180.4,
        "totalTps": 801.8666667,
        "backgroundTps": 621.4666667,
        "speedup": 1.373604061,
        "abortRate": 0,
        "p99Ms": 250.2298704,
        "p99Reduction": 0.3127801324,
        "tokens": 27030,
        "agentTpsCv": 0.009664964398,
        "nSeeds": 3,
        "resultClass": "matrix_mean",
        "bestBaseline": "OCC",
        "bestBaselineAgentTps": 131.3333333
      }
    ]
  },
  {
    "workload": "YCSB medium",
    "ratio": 1,
    "verdict": "Not a benefit result",
    "alignment": "Near baseline parity; does not support the paper's order-of-magnitude medium-contention claim.",
    "points": [
      {
        "clients": 8,
        "agentTps": 69.46666667,
        "totalTps": 69.46666667,
        "backgroundTps": 0,
        "speedup": 0.9923809524,
        "abortRate": 0.001984126984,
        "p99Ms": 155.2498388,
        "p99Reduction": -0.002389194058,
        "tokens": 27083.9521,
        "agentTpsCv": 0.07336474032,
        "nSeeds": 3,
        "resultClass": "matrix_mean",
        "bestBaseline": "OCC",
        "bestBaselineAgentTps": 70
      },
      {
        "clients": 16,
        "agentTps": 136.6666667,
        "totalTps": 136.6666667,
        "backgroundTps": 0,
        "speedup": 0.9846301635,
        "abortRate": 0.004673326853,
        "p99Ms": 165.6344592,
        "p99Reduction": -0.007762555003,
        "tokens": 27156.96711,
        "agentTpsCv": 0.03429930894,
        "nSeeds": 3,
        "resultClass": "matrix_mean",
        "bestBaseline": "Polaris",
        "bestBaselineAgentTps": 138.8
      },
      {
        "clients": 24,
        "agentTps": 198.5333333,
        "totalTps": 198.5333333,
        "backgroundTps": 0,
        "speedup": 0.9900265957,
        "abortRate": 0.003242736271,
        "p99Ms": 161.5769083,
        "p99Reduction": 0.0004713958152,
        "tokens": 27118.23855,
        "agentTpsCv": 0.02420526701,
        "nSeeds": 3,
        "resultClass": "matrix_mean",
        "bestBaseline": "2PL-wait-die",
        "bestBaselineAgentTps": 200.5333333
      },
      {
        "clients": 32,
        "agentTps": 250.8,
        "totalTps": 250.8,
        "backgroundTps": 0,
        "speedup": 0.9485627837,
        "abortRate": 0.005997088692,
        "p99Ms": 170.7775706,
        "p99Reduction": -0.04688368093,
        "tokens": 27193.18942,
        "agentTpsCv": 0.0219261995,
        "nSeeds": 3,
        "resultClass": "matrix_mean",
        "bestBaseline": "OCC",
        "bestBaselineAgentTps": 264.4
      },
      {
        "clients": 40,
        "agentTps": 289.4666667,
        "totalTps": 289.4666667,
        "backgroundTps": 0,
        "speedup": 0.9823529412,
        "abortRate": 0.006969005724,
        "p99Ms": 187.1346168,
        "p99Reduction": -0.0481007641,
        "tokens": 27219.74467,
        "agentTpsCv": 0.08364864645,
        "nSeeds": 3,
        "resultClass": "matrix_mean",
        "bestBaseline": "OCC",
        "bestBaselineAgentTps": 294.6666667
      }
    ]
  },
  {
    "workload": "YCSB medium",
    "ratio": 0.8,
    "verdict": "Do not use in main figure",
    "alignment": "Mixed wins/losses, high CV at 8 clients, and unstable P99/total-throughput curves.",
    "points": [
      {
        "clients": 8,
        "agentTps": 39.33333333,
        "totalTps": 1636.133333,
        "backgroundTps": 1596.8,
        "speedup": 1.915584416,
        "abortRate": 0.02617699408,
        "p99Ms": 1315.367929,
        "p99Reduction": 0.5746901035,
        "tokens": 27775.44227,
        "agentTpsCv": 0.2609288868,
        "nSeeds": 3,
        "resultClass": "matrix_mean",
        "bestBaseline": "Silo",
        "bestBaselineAgentTps": 20.53333333
      },
      {
        "clients": 16,
        "agentTps": 71.46666667,
        "totalTps": 957.2,
        "backgroundTps": 885.7333333,
        "speedup": 0.9588550985,
        "abortRate": 0.03530571135,
        "p99Ms": 2667.939687,
        "p99Reduction": -0.07095082223,
        "tokens": 28019.80228,
        "agentTpsCv": 0.05716997554,
        "nSeeds": 3,
        "resultClass": "matrix_mean",
        "bestBaseline": "Polaris",
        "bestBaselineAgentTps": 74.53333333
      },
      {
        "clients": 24,
        "agentTps": 96,
        "totalTps": 677.4666667,
        "backgroundTps": 581.4666667,
        "speedup": 1.190082645,
        "abortRate": 0.02630357726,
        "p99Ms": 3160.802916,
        "p99Reduction": 0.05653031733,
        "tokens": 27761.00031,
        "agentTpsCv": 0.0110239638,
        "nSeeds": 3,
        "resultClass": "matrix_mean",
        "bestBaseline": "Silo",
        "bestBaselineAgentTps": 80.66666667
      },
      {
        "clients": 32,
        "agentTps": 110.8,
        "totalTps": 395.8666667,
        "backgroundTps": 285.0666667,
        "speedup": 1.054568528,
        "abortRate": 0.01942113633,
        "p99Ms": 1761.488343,
        "p99Reduction": 0.5547691201,
        "tokens": 27566.75182,
        "agentTpsCv": 0.01083032491,
        "nSeeds": 3,
        "resultClass": "matrix_mean",
        "bestBaseline": "OCC",
        "bestBaselineAgentTps": 105.0666667
      },
      {
        "clients": 40,
        "agentTps": 109.3333333,
        "totalTps": 367.4666667,
        "backgroundTps": 258.1333333,
        "speedup": 0.9203142534,
        "abortRate": 0.02249742117,
        "p99Ms": 3570.983132,
        "p99Reduction": -0.3425209495,
        "tokens": 27652.78286,
        "agentTpsCv": 0.03196424981,
        "nSeeds": 3,
        "resultClass": "matrix_mean",
        "bestBaseline": "OCC",
        "bestBaselineAgentTps": 118.8
      }
    ]
  },
  {
    "workload": "YCSB high",
    "ratio": 1,
    "verdict": "Directional only",
    "alignment": "Curve saturates smoothly, but speedup is only 0.92-1.28x and abort reaches 30.8%.",
    "points": [
      {
        "clients": 8,
        "agentTps": 15.46666667,
        "totalTps": 15.46666667,
        "backgroundTps": 0,
        "speedup": 0.9206349208,
        "abortRate": 0.175955491,
        "p99Ms": 4949.181798,
        "p99Reduction": -0.079784798,
        "tokens": 32817.01587,
        "agentTpsCv": 0.1470579492,
        "nSeeds": 3,
        "resultClass": "matrix_mean",
        "bestBaseline": "Silo",
        "bestBaselineAgentTps": 16.8
      },
      {
        "clients": 16,
        "agentTps": 25.86666667,
        "totalTps": 25.86666667,
        "backgroundTps": 0,
        "speedup": 1.276315789,
        "abortRate": 0.1843382808,
        "p99Ms": 4651.431255,
        "p99Reduction": 0.2251263858,
        "tokens": 33164.82823,
        "agentTpsCv": 0.1778910714,
        "nSeeds": 3,
        "resultClass": "matrix_mean",
        "bestBaseline": "Silo",
        "bestBaselineAgentTps": 20.26666667
      },
      {
        "clients": 24,
        "agentTps": 29.2,
        "totalTps": 29.2,
        "backgroundTps": 0,
        "speedup": 1.223463687,
        "abortRate": 0.2458170656,
        "p99Ms": 5294.847052,
        "p99Reduction": 0.130878162,
        "tokens": 35843.08739,
        "agentTpsCv": 0.0762707447,
        "nSeeds": 3,
        "resultClass": "matrix_mean",
        "bestBaseline": "Silo",
        "bestBaselineAgentTps": 23.86666667
      },
      {
        "clients": 32,
        "agentTps": 31.86666667,
        "totalTps": 31.86666667,
        "backgroundTps": 0,
        "speedup": 1.21319797,
        "abortRate": 0.2916659945,
        "p99Ms": 6927.075003,
        "p99Reduction": 0.08801639847,
        "tokens": 38178.30733,
        "agentTpsCv": 0.2017500159,
        "nSeeds": 3,
        "resultClass": "matrix_mean",
        "bestBaseline": "Silo",
        "bestBaselineAgentTps": 26.26666667
      },
      {
        "clients": 40,
        "agentTps": 32,
        "totalTps": 32,
        "backgroundTps": 0,
        "speedup": 1.085972851,
        "abortRate": 0.3076869194,
        "p99Ms": 7546.276557,
        "p99Reduction": -0.06617866739,
        "tokens": 39043.04072,
        "agentTpsCv": 0.06959705454,
        "nSeeds": 3,
        "resultClass": "matrix_mean",
        "bestBaseline": "OCC",
        "bestBaselineAgentTps": 29.46666667
      }
    ]
  },
  {
    "workload": "YCSB high",
    "ratio": 0.8,
    "verdict": "Do not use in main figure",
    "alignment": "Large ratios rely on near-zero baselines; 24->32 has a 94% Agent-TPS jump and total/background TPS cliffs.",
    "points": [
      {
        "clients": 8,
        "agentTps": 10.53333333,
        "totalTps": 757.0666667,
        "backgroundTps": 746.5333333,
        "speedup": 26.33333332,
        "abortRate": 0.1601851852,
        "p99Ms": 4469.49346,
        "p99Reduction": 0.088821853,
        "tokens": 32229.3797,
        "agentTpsCv": 0.2799157517,
        "nSeeds": 3,
        "resultClass": "matrix_mean",
        "bestBaseline": "Silo",
        "bestBaselineAgentTps": 0.4
      },
      {
        "clients": 16,
        "agentTps": 19.06666667,
        "totalTps": 416.4,
        "backgroundTps": 397.3333333,
        "speedup": 28.6,
        "abortRate": 0.215537518,
        "p99Ms": 5410.670611,
        "p99Reduction": 0.1764718726,
        "tokens": 34457.49301,
        "agentTpsCv": 0.04367131467,
        "nSeeds": 3,
        "resultClass": "matrix_mean",
        "bestBaseline": "Silo",
        "bestBaselineAgentTps": 0.6666666667
      },
      {
        "clients": 24,
        "agentTps": 18,
        "totalTps": 524.4,
        "backgroundTps": 506.4,
        "speedup": 22.5,
        "abortRate": 0.2831933392,
        "p99Ms": 6666.874432,
        "p99Reduction": 0.02207870781,
        "tokens": 37818.64678,
        "agentTpsCv": 0.3227964233,
        "nSeeds": 3,
        "resultClass": "matrix_mean",
        "bestBaseline": "OCC",
        "bestBaselineAgentTps": 0.8
      },
      {
        "clients": 32,
        "agentTps": 35,
        "totalTps": 90,
        "backgroundTps": 55,
        "speedup": 17.5,
        "abortRate": 0.2702702703,
        "p99Ms": 4969.510444,
        "p99Reduction": 0.2965103259,
        "tokens": 37041.11111,
        "agentTpsCv": 0,
        "nSeeds": 1,
        "resultClass": "formal_mean",
        "bestBaseline": "2PL-wait-die",
        "bestBaselineAgentTps": 2
      },
      {
        "clients": 40,
        "agentTps": 40,
        "totalTps": 75,
        "backgroundTps": 35,
        "speedup": 20,
        "abortRate": 0.3402061856,
        "p99Ms": 5244.176475,
        "p99Reduction": 0.3932916952,
        "tokens": 40967.34375,
        "agentTpsCv": 0,
        "nSeeds": 1,
        "resultClass": "formal_mean",
        "bestBaseline": "Polaris",
        "bestBaselineAgentTps": 2
      }
    ]
  },
  {
    "workload": "TPC-C low",
    "ratio": 1,
    "verdict": "Auxiliary only",
    "alignment": "Monotone scaling shape, but 5x clients yields 3.62x TPS and every point is slightly below the best baseline.",
    "points": [
      {
        "clients": 8,
        "agentTps": 25.46666667,
        "totalTps": 25.46666667,
        "backgroundTps": 0,
        "speedup": 0.9845360825,
        "abortRate": 0.004329004329,
        "p99Ms": 990.1518392,
        "p99Reduction": -0.005565995227,
        "tokens": 110395.3946,
        "agentTpsCv": 0.145940941,
        "nSeeds": 3,
        "resultClass": "matrix_mean",
        "bestBaseline": "OCC",
        "bestBaselineAgentTps": 25.86666667
      },
      {
        "clients": 16,
        "agentTps": 47.33333333,
        "totalTps": 47.33333333,
        "backgroundTps": 0,
        "speedup": 0.9833795014,
        "abortRate": 0.01225322199,
        "p99Ms": 977.5764875,
        "p99Reduction": -0.0223540576,
        "tokens": 113080.2064,
        "agentTpsCv": 0.06830622903,
        "nSeeds": 3,
        "resultClass": "matrix_mean",
        "bestBaseline": "2PL-wait-die",
        "bestBaselineAgentTps": 48.13333333
      },
      {
        "clients": 24,
        "agentTps": 62.66666667,
        "totalTps": 62.66666667,
        "backgroundTps": 0,
        "speedup": 0.9611451943,
        "abortRate": 0.03070855421,
        "p99Ms": 2585.90597,
        "p99Reduction": -0.03610697954,
        "tokens": 115022.7589,
        "agentTpsCv": 0.07480168439,
        "nSeeds": 3,
        "resultClass": "matrix_mean",
        "bestBaseline": "Silo",
        "bestBaselineAgentTps": 65.2
      },
      {
        "clients": 32,
        "agentTps": 84.93333333,
        "totalTps": 84.93333333,
        "backgroundTps": 0,
        "speedup": 0.9875968992,
        "abortRate": 0.0341122244,
        "p99Ms": 3724.215683,
        "p99Reduction": 0.01657255669,
        "tokens": 114607.5912,
        "agentTpsCv": 0.05963397147,
        "nSeeds": 3,
        "resultClass": "matrix_mean",
        "bestBaseline": "OCC",
        "bestBaselineAgentTps": 86
      },
      {
        "clients": 40,
        "agentTps": 92.26666667,
        "totalTps": 92.26666667,
        "backgroundTps": 0,
        "speedup": 0.9479452055,
        "abortRate": 0.0468478786,
        "p99Ms": 4624.58193,
        "p99Reduction": 0.04001923704,
        "tokens": 112811.9178,
        "agentTpsCv": 0.08476884032,
        "nSeeds": 3,
        "resultClass": "matrix_mean",
        "bestBaseline": "OCC",
        "bestBaselineAgentTps": 97.33333333
      }
    ]
  },
  {
    "workload": "TPC-C low",
    "ratio": 0.8,
    "verdict": "Do not use in main figure",
    "alignment": "Agent TPS scales to 32 clients, then falls; only one point clearly beats the best baseline and total TPS is irregular.",
    "points": [
      {
        "clients": 8,
        "agentTps": 5.466666667,
        "totalTps": 1365.466667,
        "backgroundTps": 1360,
        "speedup": 0.9534883722,
        "abortRate": 0.2235185185,
        "p99Ms": 5678.406022,
        "p99Reduction": 0.03930789672,
        "tokens": 150896.4381,
        "agentTpsCv": 0.0844902833,
        "nSeeds": 3,
        "resultClass": "matrix_mean",
        "bestBaseline": "OCC",
        "bestBaselineAgentTps": 5.733333333
      },
      {
        "clients": 16,
        "agentTps": 17.86666667,
        "totalTps": 643.2,
        "backgroundTps": 625.3333333,
        "speedup": 1,
        "abortRate": 0.1504643506,
        "p99Ms": 5616.244675,
        "p99Reduction": -0.04035902544,
        "tokens": 131823.0877,
        "agentTpsCv": 0.1930226441,
        "nSeeds": 3,
        "resultClass": "matrix_mean",
        "bestBaseline": "2PL-wait-die",
        "bestBaselineAgentTps": 17.86666667
      },
      {
        "clients": 24,
        "agentTps": 31.46666667,
        "totalTps": 261.8666667,
        "backgroundTps": 230.4,
        "speedup": 1.185929649,
        "abortRate": 0.1014509148,
        "p99Ms": 4381.911715,
        "p99Reduction": 0.04489021054,
        "tokens": 126280.6507,
        "agentTpsCv": 0.1861033157,
        "nSeeds": 3,
        "resultClass": "matrix_mean",
        "bestBaseline": "OCC",
        "bestBaselineAgentTps": 26.53333333
      },
      {
        "clients": 32,
        "agentTps": 36.93333333,
        "totalTps": 319.4666667,
        "backgroundTps": 282.5333333,
        "speedup": 0.9172185429,
        "abortRate": 0.1174986365,
        "p99Ms": 5517.719935,
        "p99Reduction": -0.01890736618,
        "tokens": 127141.6814,
        "agentTpsCv": 0.09211083626,
        "nSeeds": 3,
        "resultClass": "matrix_mean",
        "bestBaseline": "Silo",
        "bestBaselineAgentTps": 40.26666667
      },
      {
        "clients": 40,
        "agentTps": 34,
        "totalTps": 161.7333333,
        "backgroundTps": 127.7333333,
        "speedup": 0.7846153847,
        "abortRate": 0.08311608853,
        "p99Ms": 4969.388379,
        "p99Reduction": 0.01387603588,
        "tokens": 125309.975,
        "agentTpsCv": 0.2117647059,
        "nSeeds": 3,
        "resultClass": "matrix_mean",
        "bestBaseline": "Polaris",
        "bestBaselineAgentTps": 43.33333333
      }
    ]
  },
  {
    "workload": "TPC-C high",
    "ratio": 1,
    "verdict": "Main result with caveat",
    "alignment": "Strong 1.44-3.91x Agent-TPS and large P99 gains, but abort is 27-76% and TPS declines after saturation at 16 clients.",
    "points": [
      {
        "clients": 8,
        "agentTps": 22.8,
        "totalTps": 22.8,
        "backgroundTps": 0,
        "speedup": 3.288461539,
        "abortRate": 0.2696629213,
        "p99Ms": 768.4640589,
        "p99Reduction": 0.8504517324,
        "tokens": 159998.4071,
        "agentTpsCv": 0,
        "nSeeds": 1,
        "resultClass": "formal_mean",
        "bestBaseline": "OCC",
        "bestBaselineAgentTps": 6.933333333
      },
      {
        "clients": 16,
        "agentTps": 36,
        "totalTps": 36,
        "backgroundTps": 0,
        "speedup": 3.913043478,
        "abortRate": 0.4778325123,
        "p99Ms": 943.2873204,
        "p99Reduction": 0.8774179273,
        "tokens": 230162.5278,
        "agentTpsCv": 0,
        "nSeeds": 1,
        "resultClass": "formal_mean",
        "bestBaseline": "OCC",
        "bestBaselineAgentTps": 9.2
      },
      {
        "clients": 24,
        "agentTps": 33.6,
        "totalTps": 33.6,
        "backgroundTps": 0,
        "speedup": 2.4,
        "abortRate": 0.6218181818,
        "p99Ms": 1541.583792,
        "p99Reduction": 0.8311867631,
        "tokens": 300313.2441,
        "agentTpsCv": 0,
        "nSeeds": 1,
        "resultClass": "formal_mean",
        "bestBaseline": "Silo",
        "bestBaselineAgentTps": 14
      },
      {
        "clients": 32,
        "agentTps": 28.4,
        "totalTps": 28.4,
        "backgroundTps": 0,
        "speedup": 1.868421053,
        "abortRate": 0.6607773852,
        "p99Ms": 2332.394822,
        "p99Reduction": 0.6947797698,
        "tokens": 340641.3516,
        "agentTpsCv": 0,
        "nSeeds": 1,
        "resultClass": "formal_mean",
        "bestBaseline": "2PL-wait-die",
        "bestBaselineAgentTps": 15.2
      },
      {
        "clients": 40,
        "agentTps": 20.4,
        "totalTps": 20.4,
        "backgroundTps": 0,
        "speedup": 1.443396227,
        "abortRate": 0.7586206897,
        "p99Ms": 3216.82356,
        "p99Reduction": 0.6734021965,
        "tokens": 494999.3889,
        "agentTpsCv": 0,
        "nSeeds": 1,
        "resultClass": "formal_mean",
        "bestBaseline": "2PL-wait-die",
        "bestBaselineAgentTps": 14.13333333
      }
    ]
  },
  {
    "workload": "TPC-C high",
    "ratio": 0.8,
    "verdict": "Do not use in main figure",
    "alignment": "Four speedups are undefined because baseline Agent TPS is zero; abort is 40-47% and total/background TPS collapses.",
    "points": [
      {
        "clients": 8,
        "agentTps": 0.9333333333,
        "totalTps": 761.0666667,
        "backgroundTps": 760.1333333,
        "speedup": null,
        "abortRate": 0.439869281,
        "p99Ms": 4980.483333,
        "p99Reduction": 0.06492618844,
        "tokens": 114598.0318,
        "agentTpsCv": 1.078547776,
        "nSeeds": 3,
        "resultClass": "matrix_mean",
        "bestBaseline": "OCC",
        "bestBaselineAgentTps": 0
      },
      {
        "clients": 16,
        "agentTps": 3.866666667,
        "totalTps": 216.8,
        "backgroundTps": 212.9333333,
        "speedup": null,
        "abortRate": 0.4193258937,
        "p99Ms": 7006.733112,
        "p99Reduction": -0.1942369681,
        "tokens": 182307.0073,
        "agentTpsCv": 0.3325396814,
        "nSeeds": 3,
        "resultClass": "matrix_mean",
        "bestBaseline": "OCC",
        "bestBaselineAgentTps": 0
      },
      {
        "clients": 24,
        "agentTps": 7.333333333,
        "totalTps": 71.46666667,
        "backgroundTps": 64.13333333,
        "speedup": null,
        "abortRate": 0.3951891799,
        "p99Ms": 7718.803797,
        "p99Reduction": 0.004034401265,
        "tokens": 190793.1756,
        "agentTpsCv": 0.1753391047,
        "nSeeds": 3,
        "resultClass": "matrix_mean",
        "bestBaseline": "OCC",
        "bestBaselineAgentTps": 0
      },
      {
        "clients": 32,
        "agentTps": 7.733333333,
        "totalTps": 66.93333333,
        "backgroundTps": 59.2,
        "speedup": null,
        "abortRate": 0.4559265835,
        "p99Ms": 8904.189717,
        "p99Reduction": 0.002447899134,
        "tokens": 214578.348,
        "agentTpsCv": 0.07900992578,
        "nSeeds": 3,
        "resultClass": "matrix_mean",
        "bestBaseline": "OCC",
        "bestBaselineAgentTps": 0
      },
      {
        "clients": 40,
        "agentTps": 8.133333333,
        "totalTps": 56.13333333,
        "backgroundTps": 48,
        "speedup": 61.00000001,
        "abortRate": 0.4728981336,
        "p99Ms": 8612.666871,
        "p99Reduction": 0.0948346092,
        "tokens": 212549.4446,
        "agentTpsCv": 0.07512419172,
        "nSeeds": 3,
        "resultClass": "matrix_mean",
        "bestBaseline": "OCC",
        "bestBaselineAgentTps": 0.1333333333
      }
    ]
  }
]